docs/conf.py
metaspace_converter/__init__.py
metaspace_converter/anndata_to_array.py
metaspace_converter/colocalization.py
metaspace_converter/constants.py
metaspace_converter/to_anndata.py
metaspace_converter/to_spatialdata.py
metaspace_converter/utils.py
metaspace_converter/tests/anndata_to_array_test.py
metaspace_converter/tests/colocalization_test.py
metaspace_converter/tests/to_anndata_test.py
metaspace_converter/tests/to_spatialdata_test.py
metaspace_converter/tests/utils_test.py
metaspace_converter-1.1.1.dist-info/LICENSE.txt
metaspace_converter-1.1.1.dist-info/METADATA
metaspace_converter-1.1.1.dist-info/WHEEL
metaspace_converter-1.1.1.dist-info/top_level.txt
metaspace_converter-1.1.1.dist-info/RECORD
