Metadata-Version: 2.1
Name: metaspace-converter
Version: 1.1.1
Summary: Convert Metaspace datasets to AnnData
Author-email: Tim Daniel Rose <tim.rose@embl.de>, Andreas Eisenbarth <andreas.eisenbarth@embl.de>
License: Apache-2.0
Project-URL: Repository, https://github.com/metaspace2020/metaspace-converter
Project-URL: Source, https://github.com/metaspace2020/metaspace-converter
Project-URL: Documentation, https://metaspace2020.github.io/metaspace-converter/
Classifier: License :: OSI Approved :: Apache Software License
Classifier: Topic :: Scientific/Engineering :: Bio-Informatics
Classifier: Intended Audience :: Science/Research
Classifier: Natural Language :: English
Classifier: Operating System :: MacOS
Classifier: Operating System :: Microsoft :: Windows
Classifier: Operating System :: POSIX :: Linux
Classifier: Programming Language :: Python :: 3
Classifier: Programming Language :: Python :: 3.9
Classifier: Programming Language :: Python :: 3.10
Classifier: Programming Language :: Python :: 3.11
Requires-Python: >=3.9
License-File: LICENSE.txt
Requires-Dist: anndata >=0.9.2
Requires-Dist: metaspace2020 >=2.0.6
Requires-Dist: numpy
Requires-Dist: pandas
Requires-Dist: spatial-image >=0.3
Requires-Dist: spatialdata >=0.0.15
Provides-Extra: docs
Requires-Dist: sphinx ~=7.2 ; extra == 'docs'
Requires-Dist: sphinx-autodoc-typehints ; extra == 'docs'
Requires-Dist: sphinx-codeautolink ; extra == 'docs'
Requires-Dist: sphinx-copybutton ; extra == 'docs'
Requires-Dist: sphinx-rtd-theme ; extra == 'docs'
Requires-Dist: scanpy ~=1.9.6 ; extra == 'docs'
Requires-Dist: spatialdata-plot ~=0.0.6 ; extra == 'docs'
Requires-Dist: squidpy ~=1.3.1 ; extra == 'docs'
Provides-Extra: test
Requires-Dist: multiscale-spatial-image >=0.11 ; extra == 'test'
Requires-Dist: pytest >=7.2 ; extra == 'test'
Requires-Dist: pytest-cov >=4.1 ; extra == 'test'
